{
  "ports": {
    "react-aria-components": {
      "status": "in_progress",
      "targetPackage": "@vue-spectrum/components",
      "targetPath": "packages/@vue-spectrum/components",
      "notes": "Initial Vue baseline package exists, but React Aria Components parity is still in progress.",
      "acceptanceTests": [
        {
          "name": "Vue package source lint",
          "command": "yarn eslint packages/@vue-spectrum/components/src"
        },
        {
          "name": "Vue starter typecheck",
          "command": "yarn workspace vue-spectrum-starter typecheck"
        },
        {
          "name": "Vue starter production build",
          "command": "yarn workspace vue-spectrum-starter build"
        },
        {
          "name": "Vue starter interaction tests",
          "command": "yarn test:vue"
        }
      ]
    },
    "@react-aria/virtualizer": {
      "status": "in_progress",
      "targetPackage": "@vue-aria/virtualizer",
      "targetPath": "packages/@vue-aria/virtualizer",
      "notes": "Foundational React Aria virtualizer port to support virtualized Vue collection components, now validated by starter interaction/composable tests and wired into the Vue starter virtualized backlog demo.",
      "acceptanceTests": [
        {
          "name": "Vue Aria virtualizer source lint",
          "command": "yarn eslint packages/@vue-aria/virtualizer/src"
        },
        {
          "name": "Vue starter typecheck",
          "command": "yarn workspace vue-spectrum-starter typecheck"
        },
        {
          "name": "Vue starter production build",
          "command": "yarn workspace vue-spectrum-starter build"
        },
        {
          "name": "Vue starter interaction tests",
          "command": "yarn test:vue"
        }
      ]
    },
    "@react-spectrum/provider": {
      "status": "in_progress",
      "targetPackage": "@vue-spectrum/provider",
      "targetPath": "packages/@vue-spectrum/provider",
      "notes": "First-wave target after the initial Vue baseline package, to establish theming and app-level context.",
      "acceptanceTests": [
        {
          "name": "Vue provider package source lint",
          "command": "yarn eslint packages/@vue-spectrum/provider/src"
        },
        {
          "name": "Vue starter typecheck",
          "command": "yarn workspace vue-spectrum-starter typecheck"
        },
        {
          "name": "Vue starter production build",
          "command": "yarn workspace vue-spectrum-starter build"
        }
      ]
    },
    "@react-spectrum/button": {
      "status": "in_progress",
      "targetPackage": "@vue-spectrum/button",
      "targetPath": "packages/@vue-spectrum/button",
      "notes": "First-wave primitive aligned with existing VueButton baseline work.",
      "acceptanceTests": [
        {
          "name": "Vue button package source lint",
          "command": "yarn eslint packages/@vue-spectrum/button/src"
        },
        {
          "name": "Vue starter typecheck",
          "command": "yarn workspace vue-spectrum-starter typecheck"
        },
        {
          "name": "Vue starter production build",
          "command": "yarn workspace vue-spectrum-starter build"
        }
      ]
    },
    "@react-spectrum/textfield": {
      "status": "in_progress",
      "targetPackage": "@vue-spectrum/textfield",
      "targetPath": "packages/@vue-spectrum/textfield",
      "notes": "First-wave primitive aligned with existing VueTextField baseline work.",
      "acceptanceTests": [
        {
          "name": "Vue textfield package source lint",
          "command": "yarn eslint packages/@vue-spectrum/textfield/src"
        },
        {
          "name": "Vue starter typecheck",
          "command": "yarn workspace vue-spectrum-starter typecheck"
        },
        {
          "name": "Vue starter production build",
          "command": "yarn workspace vue-spectrum-starter build"
        }
      ]
    },
    "@react-spectrum/checkbox": {
      "status": "in_progress",
      "targetPackage": "@vue-spectrum/checkbox",
      "targetPath": "packages/@vue-spectrum/checkbox",
      "notes": "First-wave primitive for form controls.",
      "acceptanceTests": [
        {
          "name": "Vue checkbox package source lint",
          "command": "yarn eslint packages/@vue-spectrum/checkbox/src"
        },
        {
          "name": "Vue starter typecheck",
          "command": "yarn workspace vue-spectrum-starter typecheck"
        },
        {
          "name": "Vue starter production build",
          "command": "yarn workspace vue-spectrum-starter build"
        }
      ]
    },
    "@react-spectrum/combobox": {
      "status": "in_progress",
      "targetPackage": "@vue-spectrum/combobox",
      "targetPath": "packages/@vue-spectrum/combobox",
      "notes": "Composition-layer migration step with an initial Vue combobox primitive.",
      "acceptanceTests": [
        {
          "name": "Vue combobox package source lint",
          "command": "yarn eslint packages/@vue-spectrum/combobox/src"
        },
        {
          "name": "Vue starter typecheck",
          "command": "yarn workspace vue-spectrum-starter typecheck"
        },
        {
          "name": "Vue starter production build",
          "command": "yarn workspace vue-spectrum-starter build"
        }
      ]
    },
    "@react-spectrum/dialog": {
      "status": "in_progress",
      "targetPackage": "@vue-spectrum/dialog",
      "targetPath": "packages/@vue-spectrum/dialog",
      "notes": "Composition-layer migration step providing a Vue dialog primitive.",
      "acceptanceTests": [
        {
          "name": "Vue dialog package source lint",
          "command": "yarn eslint packages/@vue-spectrum/dialog/src"
        },
        {
          "name": "Vue starter typecheck",
          "command": "yarn workspace vue-spectrum-starter typecheck"
        },
        {
          "name": "Vue starter production build",
          "command": "yarn workspace vue-spectrum-starter build"
        }
      ]
    },
    "@react-spectrum/divider": {
      "status": "in_progress",
      "targetPackage": "@vue-spectrum/divider",
      "targetPath": "packages/@vue-spectrum/divider",
      "notes": "First-wave visual primitive for section separation.",
      "acceptanceTests": [
        {
          "name": "Vue divider package source lint",
          "command": "yarn eslint packages/@vue-spectrum/divider/src"
        },
        {
          "name": "Vue starter typecheck",
          "command": "yarn workspace vue-spectrum-starter typecheck"
        },
        {
          "name": "Vue starter production build",
          "command": "yarn workspace vue-spectrum-starter build"
        }
      ]
    },
    "@react-spectrum/dnd": {
      "status": "in_progress",
      "targetPackage": "@vue-spectrum/dnd",
      "targetPath": "packages/@vue-spectrum/dnd",
      "notes": "Data-heavy migration baseline for drag-and-drop interactions.",
      "acceptanceTests": [
        {
          "name": "Vue dnd package source lint",
          "command": "yarn eslint packages/@vue-spectrum/dnd/src"
        },
        {
          "name": "Vue starter typecheck",
          "command": "yarn workspace vue-spectrum-starter typecheck"
        },
        {
          "name": "Vue starter production build",
          "command": "yarn workspace vue-spectrum-starter build"
        }
      ]
    },
    "@react-spectrum/form": {
      "status": "in_progress",
      "targetPackage": "@vue-spectrum/form",
      "targetPath": "packages/@vue-spectrum/form",
      "notes": "First-wave form grouping migration step with a Vue form primitive.",
      "acceptanceTests": [
        {
          "name": "Vue form package source lint",
          "command": "yarn eslint packages/@vue-spectrum/form/src"
        },
        {
          "name": "Vue starter typecheck",
          "command": "yarn workspace vue-spectrum-starter typecheck"
        },
        {
          "name": "Vue starter production build",
          "command": "yarn workspace vue-spectrum-starter build"
        }
      ]
    },
    "@react-spectrum/listbox": {
      "status": "in_progress",
      "targetPackage": "@vue-spectrum/listbox",
      "targetPath": "packages/@vue-spectrum/listbox",
      "notes": "Composition-layer migration step with an initial Vue listbox primitive.",
      "acceptanceTests": [
        {
          "name": "Vue listbox package source lint",
          "command": "yarn eslint packages/@vue-spectrum/listbox/src"
        },
        {
          "name": "Vue starter typecheck",
          "command": "yarn workspace vue-spectrum-starter typecheck"
        },
        {
          "name": "Vue starter production build",
          "command": "yarn workspace vue-spectrum-starter build"
        }
      ]
    },
    "@react-spectrum/link": {
      "status": "in_progress",
      "targetPackage": "@vue-spectrum/link",
      "targetPath": "packages/@vue-spectrum/link",
      "notes": "First-wave visual/content migration step with a Vue link primitive.",
      "acceptanceTests": [
        {
          "name": "Vue link package source lint",
          "command": "yarn eslint packages/@vue-spectrum/link/src"
        },
        {
          "name": "Vue starter typecheck",
          "command": "yarn workspace vue-spectrum-starter typecheck"
        },
        {
          "name": "Vue starter production build",
          "command": "yarn workspace vue-spectrum-starter build"
        }
      ]
    },
    "@react-spectrum/menu": {
      "status": "in_progress",
      "targetPackage": "@vue-spectrum/menu",
      "targetPath": "packages/@vue-spectrum/menu",
      "notes": "Composition-layer migration step with an initial Vue menu primitive.",
      "acceptanceTests": [
        {
          "name": "Vue menu package source lint",
          "command": "yarn eslint packages/@vue-spectrum/menu/src"
        },
        {
          "name": "Vue starter typecheck",
          "command": "yarn workspace vue-spectrum-starter typecheck"
        },
        {
          "name": "Vue starter production build",
          "command": "yarn workspace vue-spectrum-starter build"
        }
      ]
    },
    "@react-spectrum/numberfield": {
      "status": "in_progress",
      "targetPackage": "@vue-spectrum/numberfield",
      "targetPath": "packages/@vue-spectrum/numberfield",
      "notes": "First-wave primitive for numeric text entry.",
      "acceptanceTests": [
        {
          "name": "Vue numberfield package source lint",
          "command": "yarn eslint packages/@vue-spectrum/numberfield/src"
        },
        {
          "name": "Vue starter typecheck",
          "command": "yarn workspace vue-spectrum-starter typecheck"
        },
        {
          "name": "Vue starter production build",
          "command": "yarn workspace vue-spectrum-starter build"
        }
      ]
    },
    "@react-spectrum/overlays": {
      "status": "in_progress",
      "targetPackage": "@vue-spectrum/overlays",
      "targetPath": "packages/@vue-spectrum/overlays",
      "notes": "Composition-layer migration step providing a Vue popover primitive.",
      "acceptanceTests": [
        {
          "name": "Vue overlays package source lint",
          "command": "yarn eslint packages/@vue-spectrum/overlays/src"
        },
        {
          "name": "Vue starter typecheck",
          "command": "yarn workspace vue-spectrum-starter typecheck"
        },
        {
          "name": "Vue starter production build",
          "command": "yarn workspace vue-spectrum-starter build"
        }
      ]
    },
    "@react-spectrum/radio": {
      "status": "in_progress",
      "targetPackage": "@vue-spectrum/radio",
      "targetPath": "packages/@vue-spectrum/radio",
      "notes": "First-wave primitive for form controls.",
      "acceptanceTests": [
        {
          "name": "Vue radio package source lint",
          "command": "yarn eslint packages/@vue-spectrum/radio/src"
        },
        {
          "name": "Vue starter typecheck",
          "command": "yarn workspace vue-spectrum-starter typecheck"
        },
        {
          "name": "Vue starter production build",
          "command": "yarn workspace vue-spectrum-starter build"
        }
      ]
    },
    "@react-spectrum/searchfield": {
      "status": "in_progress",
      "targetPackage": "@vue-spectrum/searchfield",
      "targetPath": "packages/@vue-spectrum/searchfield",
      "notes": "First-wave primitive for search-oriented text input.",
      "acceptanceTests": [
        {
          "name": "Vue searchfield package source lint",
          "command": "yarn eslint packages/@vue-spectrum/searchfield/src"
        },
        {
          "name": "Vue starter typecheck",
          "command": "yarn workspace vue-spectrum-starter typecheck"
        },
        {
          "name": "Vue starter production build",
          "command": "yarn workspace vue-spectrum-starter build"
        }
      ]
    },
    "@react-spectrum/slider": {
      "status": "in_progress",
      "targetPackage": "@vue-spectrum/slider",
      "targetPath": "packages/@vue-spectrum/slider",
      "notes": "First-wave primitive for range input controls.",
      "acceptanceTests": [
        {
          "name": "Vue slider package source lint",
          "command": "yarn eslint packages/@vue-spectrum/slider/src"
        },
        {
          "name": "Vue starter typecheck",
          "command": "yarn workspace vue-spectrum-starter typecheck"
        },
        {
          "name": "Vue starter production build",
          "command": "yarn workspace vue-spectrum-starter build"
        }
      ]
    },
    "@react-spectrum/progress": {
      "status": "in_progress",
      "targetPackage": "@vue-spectrum/progress",
      "targetPath": "packages/@vue-spectrum/progress",
      "notes": "First-wave primitive for progress feedback UI.",
      "acceptanceTests": [
        {
          "name": "Vue progress package source lint",
          "command": "yarn eslint packages/@vue-spectrum/progress/src"
        },
        {
          "name": "Vue starter typecheck",
          "command": "yarn workspace vue-spectrum-starter typecheck"
        },
        {
          "name": "Vue starter production build",
          "command": "yarn workspace vue-spectrum-starter build"
        }
      ]
    },
    "@react-spectrum/meter": {
      "status": "in_progress",
      "targetPackage": "@vue-spectrum/meter",
      "targetPath": "packages/@vue-spectrum/meter",
      "notes": "First-wave primitive for bounded measurements.",
      "acceptanceTests": [
        {
          "name": "Vue meter package source lint",
          "command": "yarn eslint packages/@vue-spectrum/meter/src"
        },
        {
          "name": "Vue starter typecheck",
          "command": "yarn workspace vue-spectrum-starter typecheck"
        },
        {
          "name": "Vue starter production build",
          "command": "yarn workspace vue-spectrum-starter build"
        }
      ]
    },
    "@react-spectrum/statuslight": {
      "status": "in_progress",
      "targetPackage": "@vue-spectrum/statuslight",
      "targetPath": "packages/@vue-spectrum/statuslight",
      "notes": "First-wave primitive for lightweight status signaling.",
      "acceptanceTests": [
        {
          "name": "Vue statuslight package source lint",
          "command": "yarn eslint packages/@vue-spectrum/statuslight/src"
        },
        {
          "name": "Vue starter typecheck",
          "command": "yarn workspace vue-spectrum-starter typecheck"
        },
        {
          "name": "Vue starter production build",
          "command": "yarn workspace vue-spectrum-starter build"
        }
      ]
    },
    "@react-spectrum/table": {
      "status": "in_progress",
      "targetPackage": "@vue-spectrum/table",
      "targetPath": "packages/@vue-spectrum/table",
      "notes": "Data-heavy migration baseline for tabular collections.",
      "acceptanceTests": [
        {
          "name": "Vue table package source lint",
          "command": "yarn eslint packages/@vue-spectrum/table/src"
        },
        {
          "name": "Vue starter typecheck",
          "command": "yarn workspace vue-spectrum-starter typecheck"
        },
        {
          "name": "Vue starter production build",
          "command": "yarn workspace vue-spectrum-starter build"
        }
      ]
    },
    "@react-spectrum/tree": {
      "status": "in_progress",
      "targetPackage": "@vue-spectrum/tree",
      "targetPath": "packages/@vue-spectrum/tree",
      "notes": "Data-heavy migration baseline for hierarchical collections.",
      "acceptanceTests": [
        {
          "name": "Vue tree package source lint",
          "command": "yarn eslint packages/@vue-spectrum/tree/src"
        },
        {
          "name": "Vue starter typecheck",
          "command": "yarn workspace vue-spectrum-starter typecheck"
        },
        {
          "name": "Vue starter production build",
          "command": "yarn workspace vue-spectrum-starter build"
        }
      ]
    },
    "@react-spectrum/switch": {
      "status": "in_progress",
      "targetPackage": "@vue-spectrum/switch",
      "targetPath": "packages/@vue-spectrum/switch",
      "notes": "First-wave primitive for binary toggles.",
      "acceptanceTests": [
        {
          "name": "Vue switch package source lint",
          "command": "yarn eslint packages/@vue-spectrum/switch/src"
        },
        {
          "name": "Vue starter typecheck",
          "command": "yarn workspace vue-spectrum-starter typecheck"
        },
        {
          "name": "Vue starter production build",
          "command": "yarn workspace vue-spectrum-starter build"
        }
      ]
    },
    "tailwindcss-react-aria-components": {
      "status": "in_progress",
      "targetPackage": "tailwindcss-vue-aria-components",
      "targetPath": "packages/tailwindcss-vue-aria-components",
      "notes": "Tailwind plugin baseline for Vue Aria-style data attribute variants.",
      "acceptanceTests": [
        {
          "name": "Vue Tailwind plugin source lint",
          "command": "yarn eslint packages/tailwindcss-vue-aria-components/src"
        },
        {
          "name": "Vue Tailwind plugin module load",
          "command": "node -e \"require('./packages/tailwindcss-vue-aria-components/src/index.js')\""
        }
      ]
    },
    "react-aria": {
      "status": "blocked",
      "notes": "Meta-package migration depends on a critical mass of @vue-aria package ports."
    },
    "react-stately": {
      "status": "blocked",
      "notes": "Meta-package migration depends on foundational @vue-stately package ports."
    }
  }
}
